doc/Makefile
doc/README.rst
doc/api-backend.rst
doc/api-model.rst
doc/api-r.rst
doc/api.rst
doc/bibliography.rst
doc/cli.rst
doc/conf.py
doc/contributing.rst
doc/contributor_license.rst
doc/data-model.rst
doc/file-io.rst
doc/index.rst
doc/install.rst
doc/make.bat
doc/notice.rst
doc/references.bib
doc/reporting.rst
doc/requirements.in
doc/requirements.txt
doc/tutorials.rst
doc/whatsnew.rst
doc/_static/IIASA_logo.png
doc/_static/combined-logo-white.png
doc/_static/combined-logo-white.svg
doc/_static/custom.css
doc/_static/favicon.svg
doc/_static/ix_components.png
doc/_static/ix_features.svg
doc/_static/ixmp-logo-white.svg
doc/_static/logo_white.png
doc/_static/report-1.dot
ixmp/__init__.py
ixmp/_config.py
ixmp/cli.py
ixmp/py.typed
ixmp/types.py
ixmp/backend/__init__.py
ixmp/backend/base.py
ixmp/backend/common.py
ixmp/backend/io.py
ixmp/backend/ixmp4.py
ixmp/backend/ixmp4_io.py
ixmp/backend/jdbc.py
ixmp/backend/jdbc/GAMSJavaAPI.jar
ixmp/backend/jdbc/HikariCP-3.4.5.jar
ixmp/backend/jdbc/activation-1.1.jar
ixmp/backend/jdbc/cfg4j-core-4.4.1.jar
ixmp/backend/jdbc/commons-collections4-4.4.jar
ixmp/backend/jdbc/commons-csv-1.6.jar
ixmp/backend/jdbc/commons-lang-2.6.jar
ixmp/backend/jdbc/flyway-core-5.1.4.jar
ixmp/backend/jdbc/hk2-api-2.6.1.jar
ixmp/backend/jdbc/hk2-locator-2.6.1.jar
ixmp/backend/jdbc/hk2-utils-2.6.1.jar
ixmp/backend/jdbc/hsqldb-2.5.1.jar
ixmp/backend/jdbc/ixmp.jar
ixmp/backend/jdbc/jackson-annotations-2.9.8.jar
ixmp/backend/jdbc/jackson-core-2.9.6.jar
ixmp/backend/jdbc/jackson-databind-2.9.6.jar
ixmp/backend/jdbc/jackson-module-jaxb-annotations-2.9.8.jar
ixmp/backend/jdbc/jakarta.annotation-api-1.3.4.jar
ixmp/backend/jdbc/jakarta.inject-2.6.1.jar
ixmp/backend/jdbc/javax.ws.rs-api-2.1.1.jar
ixmp/backend/jdbc/jaxb-api-2.3.0.jar
ixmp/backend/jdbc/jaxb-core-2.3.0.jar
ixmp/backend/jdbc/jaxb-impl-2.3.0.jar
ixmp/backend/jdbc/jersey-client-2.31.jar
ixmp/backend/jdbc/jersey-common-2.31.jar
ixmp/backend/jdbc/jersey-entity-filtering-2.31.jar
ixmp-3.11.1.dist-info/licenses/AUTHORS.md
ixmp-3.11.1.dist-info/licenses/LICENSE
ixmp-3.11.1.dist-info/licenses/NOTICE.rst
ixmp-3.11.1.dist-info/METADATA
ixmp-3.11.1.dist-info/WHEEL
ixmp-3.11.1.dist-info/entry_points.txt
ixmp-3.11.1.dist-info/top_level.txt
ixmp-3.11.1.dist-info/RECORD
