Metadata-Version: 2.4
Name: ixmp
Version: 3.11.1
Summary: The ix modeling platform
Author: IIASA Energy, Climate, and Environment (ECE) program
Maintainer-email: Paul Natsuo Kishimoto <mail@paul.kishimoto.name>, Fridolin Glatter <glatter@iiasa.ac.at>
License-Expression: Apache-2.0
Project-URL: Documentation, https://docs.messageix.org/ixmp
Project-URL: Release notes, https://docs.messageix.org/projects/ixmp/en/stable/whatsnew.html
Project-URL: Repository, https://github.com/iiasa/ixmp
Project-URL: Issue tracker, https://github.com/iiasa/ixmp/issues
Classifier: Development Status :: 5 - Production/Stable
Classifier: Intended Audience :: Developers
Classifier: Intended Audience :: Science/Research
Classifier: Natural Language :: English
Classifier: Operating System :: OS Independent
Classifier: Programming Language :: Python
Classifier: Programming Language :: Python :: 3
Classifier: Programming Language :: Python :: 3.9
Classifier: Programming Language :: Python :: 3.10
Classifier: Programming Language :: Python :: 3.11
Classifier: Programming Language :: Python :: 3.12
Classifier: Programming Language :: Python :: 3.13
Classifier: Programming Language :: R
Classifier: Topic :: Scientific/Engineering
Classifier: Topic :: Scientific/Engineering :: Information Analysis
Requires-Python: >=3.9
License-File: LICENSE
License-File: NOTICE.rst
License-File: AUTHORS.md
Requires-Dist: click
Requires-Dist: genno>=1.20
Requires-Dist: importlib_metadata; python_version < "3.10"
Requires-Dist: JPype1>=1.2.1
Requires-Dist: JPype1<=1.4.0; python_version < "3.11"
Requires-Dist: openpyxl
Requires-Dist: pandas>=1.2
Requires-Dist: pint
Requires-Dist: PyYAML
Requires-Dist: xarray
Provides-Extra: docs
Requires-Dist: ixmp[tests]; extra == "docs"
Requires-Dist: genno>=1.26; extra == "docs"
Requires-Dist: GitPython; extra == "docs"
Requires-Dist: numpydoc; extra == "docs"
Requires-Dist: sphinx>=3.0; extra == "docs"
Requires-Dist: sphinx_rtd_theme; extra == "docs"
Requires-Dist: sphinxcontrib-bibtex; extra == "docs"
Provides-Extra: ixmp4
Requires-Dist: ixmp4<0.11,>=0.10; python_version > "3.9" and extra == "ixmp4"
Requires-Dist: gamsapi[core,transfer]>=45.7.0; extra == "ixmp4"
Provides-Extra: report
Requires-Dist: genno[compat,graphviz]; extra == "report"
Provides-Extra: tutorial
Requires-Dist: jupyter; extra == "tutorial"
Provides-Extra: tests
Requires-Dist: ixmp[ixmp4,report,tutorial]; extra == "tests"
Requires-Dist: memory_profiler; extra == "tests"
Requires-Dist: nbclient>=0.5; extra == "tests"
Requires-Dist: pytest>=5; extra == "tests"
Requires-Dist: pytest-benchmark; extra == "tests"
Requires-Dist: pytest-cov; extra == "tests"
Requires-Dist: pytest-httpserver; extra == "tests"
Requires-Dist: pytest-rerunfailures; extra == "tests"
Requires-Dist: pytest-xdist; extra == "tests"
Dynamic: license-file
